<?xml version="1.0" encoding="utf-8"?><ArrayOfShape xmlns:xsi="http://www.w3.org/2001/XMLSchema-instance" xmlns:xsd="http://www.w3.org/2001/XMLSchema"><Shape xsi:type="Circle"><Radius>2.5</Radius><Height>0</Height><Width>0</Width><Colour>Red</Colour><Area>19.634954084936208</Area></Shape><Shape xsi:type="Rectangle"><Radius>0</Radius><Height>20</Height><Width>10</Width><Colour>Blue</Colour><Area>200</Area></Shape><Shape xsi:type="Circle"><Radius>8</Radius><Height>0</Height><Width>0</Width><Colour>Green</Colour><Area>201.06192982974676</Area></Shape><Shape xsi:type="Circle"><Radius>12.3</Radius><Height>0</Height><Width>0</Width><Colour>Purple</Colour><Area>475.2915525615999</Area></Shape><Shape xsi:type="Rectangle"><Radius>0</Radius><Height>45</Height><Width>18</Width><Colour>Blue</Colour><Area>810</Area></Shape></ArrayOfShape>